[
  {
    "provider_id": "PRV50514819",
    "npi": "1072784864",
    "first_name": "Matthew",
    "last_name": "Flores",
    "credentials": "MD",
    "specialty": "Orthopedics",
    "department": "Orthopedics",
    "email": "matthew.flores@hospital.org",
    "phone": "223-548-8160",
    "facility_name": "University Medical Center",
    "is_active": true,
    "license_number": "LIC48321011",
    "license_state": "TX",
    "license_expiry": "2026-07-03",
    "created_at": "2026-01-01T18:56:02.037868"
  },
  {
    "provider_id": "PRV60917201",
    "npi": "8298025255",
    "first_name": "Karen",
    "last_name": "Martin",
    "credentials": "PA",
    "specialty": "Neurology",
    "department": "Neurology",
    "email": "karen.martin@hospital.org",
    "phone": "475-262-6215",
    "facility_name": "Community Hospital",
    "is_active": true,
    "license_number": "LIC50069055",
    "license_state": "TX",
    "license_expiry": "2027-05-20",
    "created_at": "2026-01-01T18:56:02.037881"
  },
  {
    "provider_id": "PRV40629397",
    "npi": "5494048290",
    "first_name": "Thomas",
    "last_name": "Martin",
    "credentials": "PA",
    "specialty": "Dermatology",
    "department": "Dermatology",
    "email": "thomas.martin@hospital.org",
    "phone": "693-479-5110",
    "facility_name": "St. Mary's Hospital",
    "is_active": true,
    "license_number": "LIC33655075",
    "license_state": "CA",
    "license_expiry": "2026-07-03",
    "created_at": "2026-01-01T18:56:02.037893"
  },
  {
    "provider_id": "PRV87982588",
    "npi": "9697263293",
    "first_name": "Ronald",
    "last_name": "Hall",
    "credentials": "PA",
    "specialty": "Family Medicine",
    "department": "Family Medicine",
    "email": "ronald.hall@hospital.org",
    "phone": "336-861-1033",
    "facility_name": "Memorial Medical Center",
    "is_active": true,
    "license_number": "LIC49648775",
    "license_state": "OR",
    "license_expiry": "2026-06-08",
    "created_at": "2026-01-01T18:56:02.037903"
  },
  {
    "provider_id": "PRV66388317",
    "npi": "6049420293",
    "first_name": "Patricia",
    "last_name": "Kumar",
    "credentials": "MD",
    "specialty": "Infectious Disease",
    "department": "Infectious Disease",
    "email": "patricia.kumar@hospital.org",
    "phone": "828-840-5967",
    "facility_name": "St. Mary's Hospital",
    "is_active": true,
    "license_number": "LIC29904760",
    "license_state": "OR",
    "license_expiry": "2028-03-22",
    "created_at": "2026-01-01T18:56:02.037913"
  },
  {
    "provider_id": "PRV54565650",
    "npi": "1025257169",
    "first_name": "Joseph",
    "last_name": "Yamamoto",
    "credentials": "DO",
    "specialty": "Pulmonology",
    "department": "Pulmonology",
    "email": "joseph.yamamoto@hospital.org",
    "phone": "745-829-5143",
    "facility_name": "St. Mary's Hospital",
    "is_active": true,
    "license_number": "LIC54969094",
    "license_state": "OH",
    "license_expiry": "2027-07-16",
    "created_at": "2026-01-01T18:56:02.037922"
  },
  {
    "provider_id": "PRV43782244",
    "npi": "0105079402",
    "first_name": "Jessica",
    "last_name": "Baker",
    "credentials": "MD",
    "specialty": "Orthopedics",
    "department": "Orthopedics",
    "email": "jessica.baker@hospital.org",
    "phone": "518-264-2584",
    "facility_name": "City General Hospital",
    "is_active": true,
    "license_number": "LIC48563212",
    "license_state": "TX",
    "license_expiry": "2026-04-22",
    "created_at": "2026-01-01T18:56:02.037932"
  },
  {
    "provider_id": "PRV20540419",
    "npi": "9386708064",
    "first_name": "Kevin",
    "last_name": "King",
    "credentials": "MD",
    "specialty": "Rheumatology",
    "department": "Rheumatology",
    "email": "kevin.king@hospital.org",
    "phone": "257-772-1855",
    "facility_name": "Regional Health System",
    "is_active": true,
    "license_number": "LIC84648764",
    "license_state": "NC",
    "license_expiry": "2028-05-26",
    "created_at": "2026-01-01T18:56:02.037941"
  },
  {
    "provider_id": "PRV97431150",
    "npi": "7156247427",
    "first_name": "Richard",
    "last_name": "Perez",
    "credentials": "MD",
    "specialty": "Oncology",
    "department": "Oncology",
    "email": "richard.perez@hospital.org",
    "phone": "519-798-8140",
    "facility_name": "Memorial Medical Center",
    "is_active": true,
    "license_number": "LIC97387133",
    "license_state": "FL",
    "license_expiry": "2026-01-17",
    "created_at": "2026-01-01T18:56:02.037950"
  },
  {
    "provider_id": "PRV58841297",
    "npi": "3669535964",
    "first_name": "Charles",
    "last_name": "Brown",
    "credentials": "MD",
    "specialty": "Endocrinology",
    "department": "Endocrinology",
    "email": "charles.brown@hospital.org",
    "phone": "665-243-9125",
    "facility_name": "University Medical Center",
    "is_active": true,
    "license_number": "LIC96642478",
    "license_state": "MI",
    "license_expiry": "2028-02-09",
    "created_at": "2026-01-01T18:56:02.037960"
  },
  {
    "provider_id": "PRV80035146",
    "npi": "9391222182",
    "first_name": "Anthony",
    "last_name": "Sanchez",
    "credentials": "MD",
    "specialty": "Cardiology",
    "department": "Cardiology",
    "email": "anthony.sanchez@hospital.org",
    "phone": "380-468-2657",
    "facility_name": "City General Hospital",
    "is_active": true,
    "license_number": "LIC81683243",
    "license_state": "FL",
    "license_expiry": "2026-12-17",
    "created_at": "2026-01-01T18:56:02.037969"
  },
  {
    "provider_id": "PRV01971335",
    "npi": "9206157307",
    "first_name": "Sharon",
    "last_name": "Mueller",
    "credentials": "NP",
    "specialty": "Nephrology",
    "department": "Nephrology",
    "email": "sharon.mueller@hospital.org",
    "phone": "720-798-9011",
    "facility_name": "University Medical Center",
    "is_active": true,
    "license_number": "LIC77761387",
    "license_state": "FL",
    "license_expiry": "2028-10-18",
    "created_at": "2026-01-01T18:56:02.037979"
  },
  {
    "provider_id": "PRV75494567",
    "npi": "6284224318",
    "first_name": "Priya",
    "last_name": "Lopez",
    "credentials": "MD",
    "specialty": "Gastroenterology",
    "department": "Gastroenterology",
    "email": "priya.lopez@hospital.org",
    "phone": "286-337-2376",
    "facility_name": "Regional Health System",
    "is_active": true,
    "license_number": "LIC43546444",
    "license_state": "CA",
    "license_expiry": "2027-10-12",
    "created_at": "2026-01-01T18:56:02.037989"
  },
  {
    "provider_id": "PRV12630856",
    "npi": "7900021338",
    "first_name": "Paul",
    "last_name": "Harris",
    "credentials": "DO",
    "specialty": "Internal Medicine",
    "department": "Internal Medicine",
    "email": "paul.harris@hospital.org",
    "phone": "481-395-3258",
    "facility_name": "St. Mary's Hospital",
    "is_active": true,
    "license_number": "LIC79028744",
    "license_state": "CO",
    "license_expiry": "2026-01-25",
    "created_at": "2026-01-01T18:56:02.037998"
  },
  {
    "provider_id": "PRV99827225",
    "npi": "5483084944",
    "first_name": "Mohammed",
    "last_name": "Adams",
    "credentials": "NP",
    "specialty": "Orthopedics",
    "department": "Orthopedics",
    "email": "mohammed.adams@hospital.org",
    "phone": "230-583-3276",
    "facility_name": "Memorial Medical Center",
    "is_active": true,
    "license_number": "LIC83746324",
    "license_state": "TX",
    "license_expiry": "2027-09-06",
    "created_at": "2026-01-01T18:56:02.038008"
  },
  {
    "provider_id": "PRV50199579",
    "npi": "5339034396",
    "first_name": "Dorothy",
    "last_name": "Nguyen",
    "credentials": "MD",
    "specialty": "Internal Medicine",
    "department": "Internal Medicine",
    "email": "dorothy.nguyen@hospital.org",
    "phone": "375-306-3910",
    "facility_name": "City General Hospital",
    "is_active": true,
    "license_number": "LIC86019322",
    "license_state": "IN",
    "license_expiry": "2026-05-24",
    "created_at": "2026-01-01T18:56:02.038017"
  },
  {
    "provider_id": "PRV51841154",
    "npi": "0981247469",
    "first_name": "Raj",
    "last_name": "Brown",
    "credentials": "MD",
    "specialty": "Gastroenterology",
    "department": "Gastroenterology",
    "email": "raj.brown@hospital.org",
    "phone": "714-933-8519",
    "facility_name": "Regional Health System",
    "is_active": true,
    "license_number": "LIC29486235",
    "license_state": "CA",
    "license_expiry": "2028-07-31",
    "created_at": "2026-01-01T18:56:02.038027"
  },
  {
    "provider_id": "PRV72847726",
    "npi": "8128749153",
    "first_name": "Priya",
    "last_name": "Torres",
    "credentials": "PA",
    "specialty": "Internal Medicine",
    "department": "Internal Medicine",
    "email": "priya.torres@hospital.org",
    "phone": "445-361-5485",
    "facility_name": "St. Mary's Hospital",
    "is_active": true,
    "license_number": "LIC56079947",
    "license_state": "TX",
    "license_expiry": "2028-01-26",
    "created_at": "2026-01-01T18:56:02.038036"
  },
  {
    "provider_id": "PRV57412006",
    "npi": "6433102716",
    "first_name": "Elizabeth",
    "last_name": "Chen",
    "credentials": "MD",
    "specialty": "Family Medicine",
    "department": "Family Medicine",
    "email": "elizabeth.chen@hospital.org",
    "phone": "672-269-2352",
    "facility_name": "Memorial Medical Center",
    "is_active": true,
    "license_number": "LIC67442186",
    "license_state": "PA",
    "license_expiry": "2027-08-26",
    "created_at": "2026-01-01T18:56:02.038045"
  },
  {
    "provider_id": "PRV30761320",
    "npi": "6268867833",
    "first_name": "Jessica",
    "last_name": "Wright",
    "credentials": "MD",
    "specialty": "Nephrology",
    "department": "Nephrology",
    "email": "jessica.wright@hospital.org",
    "phone": "204-249-7183",
    "facility_name": "University Medical Center",
    "is_active": true,
    "license_number": "LIC93204931",
    "license_state": "GA",
    "license_expiry": "2026-05-10",
    "created_at": "2026-01-01T18:56:02.038055"
  },
  {
    "provider_id": "PRV78114135",
    "npi": "1259123143",
    "first_name": "Mark",
    "last_name": "Mueller",
    "credentials": "MD",
    "specialty": "Family Medicine",
    "department": "Family Medicine",
    "email": "mark.mueller@hospital.org",
    "phone": "669-425-2081",
    "facility_name": "St. Mary's Hospital",
    "is_active": true,
    "license_number": "LIC86302359",
    "license_state": "TX",
    "license_expiry": "2026-12-18",
    "created_at": "2026-01-01T18:56:02.038064"
  },
  {
    "provider_id": "PRV36397117",
    "npi": "6960094575",
    "first_name": "Steven",
    "last_name": "Miller",
    "credentials": "DO",
    "specialty": "Dermatology",
    "department": "Dermatology",
    "email": "steven.miller@hospital.org",
    "phone": "213-438-1347",
    "facility_name": "Memorial Medical Center",
    "is_active": true,
    "license_number": "LIC71242014",
    "license_state": "TX",
    "license_expiry": "2026-11-07",
    "created_at": "2026-01-01T18:56:02.038076"
  },
  {
    "provider_id": "PRV09597326",
    "npi": "7596208325",
    "first_name": "Timothy",
    "last_name": "Wilson",
    "credentials": "PA",
    "specialty": "Oncology",
    "department": "Oncology",
    "email": "timothy.wilson@hospital.org",
    "phone": "880-454-4644",
    "facility_name": "Memorial Medical Center",
    "is_active": true,
    "license_number": "LIC85160490",
    "license_state": "AZ",
    "license_expiry": "2027-02-23",
    "created_at": "2026-01-01T18:56:02.038085"
  },
  {
    "provider_id": "PRV58920737",
    "npi": "2122462709",
    "first_name": "Thomas",
    "last_name": "Garcia",
    "credentials": "MD",
    "specialty": "Cardiology",
    "department": "Cardiology",
    "email": "thomas.garcia@hospital.org",
    "phone": "371-682-8231",
    "facility_name": "Community Hospital",
    "is_active": true,
    "license_number": "LIC57787038",
    "license_state": "CA",
    "license_expiry": "2026-11-09",
    "created_at": "2026-01-01T18:56:02.038095"
  },
  {
    "provider_id": "PRV44360141",
    "npi": "1057499934",
    "first_name": "Daniel",
    "last_name": "Taylor",
    "credentials": "DO",
    "specialty": "Neurology",
    "department": "Neurology",
    "email": "daniel.taylor@hospital.org",
    "phone": "802-272-7697",
    "facility_name": "City General Hospital",
    "is_active": true,
    "license_number": "LIC91917977",
    "license_state": "FL",
    "license_expiry": "2028-11-09",
    "created_at": "2026-01-01T18:56:02.038104"
  },
  {
    "provider_id": "PRV30342493",
    "npi": "7061691256",
    "first_name": "Carlos",
    "last_name": "Green",
    "credentials": "MD",
    "specialty": "Nephrology",
    "department": "Nephrology",
    "email": "carlos.green@hospital.org",
    "phone": "319-989-2512",
    "facility_name": "St. Mary's Hospital",
    "is_active": true,
    "license_number": "LIC73790981",
    "license_state": "OH",
    "license_expiry": "2027-06-02",
    "created_at": "2026-01-01T18:56:02.038114"
  },
  {
    "provider_id": "PRV63348706",
    "npi": "7317933980",
    "first_name": "Joshua",
    "last_name": "Allen",
    "credentials": "MD",
    "specialty": "Orthopedics",
    "department": "Orthopedics",
    "email": "joshua.allen@hospital.org",
    "phone": "913-627-9600",
    "facility_name": "Community Hospital",
    "is_active": true,
    "license_number": "LIC67137119",
    "license_state": "NC",
    "license_expiry": "2027-03-12",
    "created_at": "2026-01-01T18:56:02.038123"
  },
  {
    "provider_id": "PRV78198491",
    "npi": "6001002470",
    "first_name": "Lisa",
    "last_name": "Gonzalez",
    "credentials": "MD",
    "specialty": "Internal Medicine",
    "department": "Internal Medicine",
    "email": "lisa.gonzalez@hospital.org",
    "phone": "207-881-1685",
    "facility_name": "City General Hospital",
    "is_active": true,
    "license_number": "LIC27359247",
    "license_state": "MA",
    "license_expiry": "2028-05-29",
    "created_at": "2026-01-01T18:56:02.038133"
  },
  {
    "provider_id": "PRV89896303",
    "npi": "3146781682",
    "first_name": "Carol",
    "last_name": "White",
    "credentials": "DO",
    "specialty": "Oncology",
    "department": "Oncology",
    "email": "carol.white@hospital.org",
    "phone": "454-577-8404",
    "facility_name": "Memorial Medical Center",
    "is_active": true,
    "license_number": "LIC68560693",
    "license_state": "OR",
    "license_expiry": "2028-01-08",
    "created_at": "2026-01-01T18:56:02.038142"
  },
  {
    "provider_id": "PRV34646049",
    "npi": "9989721155",
    "first_name": "Jennifer",
    "last_name": "Patel",
    "credentials": "NP",
    "specialty": "Nephrology",
    "department": "Nephrology",
    "email": "jennifer.patel@hospital.org",
    "phone": "716-232-3094",
    "facility_name": "Community Hospital",
    "is_active": true,
    "license_number": "LIC73658141",
    "license_state": "GA",
    "license_expiry": "2027-05-09",
    "created_at": "2026-01-01T18:56:02.038156"
  }
]